CHANGES.txt
INSTALL.txt
LICENCE.txt
MANIFEST.in
README.txt
setup.py
BinTools.egg-info/PKG-INFO
BinTools.egg-info/SOURCES.txt
BinTools.egg-info/dependency_links.txt
BinTools.egg-info/top_level.txt
bin/dwarfdump.py
bin/dwarfquery.py
bin/dwarfviewer.py
bin/readelf.py
bintools/__init__.py
bintools/dwarf/__init__.py
bintools/dwarf/abbrev.py
bintools/dwarf/aranges.py
bintools/dwarf/enums.py
bintools/dwarf/expressions.py
bintools/dwarf/frame.py
bintools/dwarf/info.py
bintools/dwarf/line.py
bintools/dwarf/loc.py
bintools/dwarf/pubnames.py
bintools/dwarf/ranges.py
bintools/dwarf/stream.py
bintools/dwarf/viewer.py
bintools/elf/__init__.py
bintools/elf/enums.py
bintools/elf/exception.py
bintools/elf/stream.py
bintools/elf/structs.py
bintools/gdb/readme.txt
bintools/utils/__init__.py