Metadata-Version: 1.0
Name: BinTools
Version: 0.2.0
Summary: Toolkit for Elf / Dwarf handling.
Home-page: http://code.google.com/p/pydevtools/
Author: Emilio Monti
Author-email: emilmont@gmail.com
License: LICENSE.txt
Platform: UNKNOWN
